{
  "imager": {
    "latest_version": "2.0.0",
    "url": "https://www.beagleboard.org/distros.json",
    "devices": [
      {
        "name": "No filtering",
        "tags": [],
        "default": false,
        "description": "Show every possible image",
        "matching_type": "inclusive"
      },
      {
        "name": "BeagleY-AI",
        "tags": [
          "beagle-am67"
        ],
        "default": false,
        "icon": "https://www.beagleboard.org/app/uploads/2024/06/beagley-ai.svg",
        "description": "BeagleY-AI based on TI AM67A",
        "matching_type": "inclusive"
      },
      {
        "name": "BeaglePlay",
        "tags": [
          "beagle-am62"
        ],
        "default": false,
        "icon": "https://www.beagleboard.org/app/uploads/2024/03/image6.png",
        "description": "BeaglePlay and other boards based on TI AM62",
        "matching_type": "inclusive"
      },
      {
        "name": "PocketBeagle 2",
        "tags": [
          "pocketbeagle2-am62"
        ],
        "default": false,
        "icon": "https://openbeagle.org/lorforlinux/docs.beagleboard.io/-/raw/main/boards/pocketbeagle-2/images/product/pocketbeagle-2-45-front.jpg",
        "description": "PocketBeagle 2 and other boards based on TI AM62",
        "matching_type": "inclusive"
      },
      {
        "name": "BeagleBone AI-64",
        "tags": [
          "beagle-tda4vm"
        ],
        "default": false,
        "icon": "https://www.beagleboard.org/app/uploads/2024/06/bbai64-front-a-2.png",
        "description": "BeagleBone AI-64 based on TI TDA4VM",
        "matching_type": "inclusive"
      },
      {
        "name": "BeagleV-Fire",
        "tags": [
          "beaglev-fire"
        ],
        "default": false,
        "icon": "https://www.beagleboard.org/app/uploads/2023/10/1-102110898-BeagleV-Fire-45-degree-front.jpg",
        "description": "BeagleV-Fire based on Microchip PolarFire SoC",
        "matching_type": "inclusive"
      },
      {
        "name": "BeagleBone Black",
        "tags": [
          "beagle-am335"
        ],
        "default": false,
        "icon": "https://www.beagleboard.org/app/uploads/2022/10/product_beaglebone_black.jpg",
        "description": "BeagleBone Black and other boards based on TI AM335",
        "matching_type": "inclusive"
      }
    ]
  },
  "os_list": [
    {
      "name": "BeagleY-AI Debian v6.1.x-ti XFCE (Recommended)",
      "description": "Debian Bookworm with the Xfce Desktop for BeagleY-AI based on TI AM67A (J722S) processor",
      "icon": "https://www.beagleboard.org/app/uploads/2022/10/debian.png",
      "url": "https://files.beagle.cc/file/beagleboard-public-2021/images/beagley-ai-debian-12.11-xfce-v6.1-arm64-2025-06-30-12gb.img.xz",
      "extract_size": 12884901888,
      "extract_sha256": "53aeef2d04e34e8d39d5f76a4be4ab805b4e4e487260887250ce639e7adfd3d3",
      "image_download_size": 1399371088,
      "image_download_sha256": "392ea78112bd53f87a8d63d9f75545849a3138256225a58b268a6cc667f23cb7",
      "release_date": "2025-06-30",
      "init_format": "sysconf",
      "devices": [
        "beagle-am67",
        "recommended"
      ]
    },
    {
      "name": "BeagleY-AI Debian v6.1.x-ti Minimal",
      "description": "Debian Bookworm with no desktop environment for BeagleY-AI based on TI AM67A (J722S) processor",
      "icon": "https://www.beagleboard.org/app/uploads/2022/10/debian.png",
      "url": "https://files.beagle.cc/file/beagleboard-public-2021/images/beagley-ai-debian-12.11-minimal-v6.1-arm64-2025-06-30-8gb.img.xz",
      "extract_size": 7818182656,
      "extract_sha256": "fdb756d32658848aff3e44fc107cd9accab7c836929d6df53195f21ca1f24f10",
      "image_download_size": 613709780,
      "image_download_sha256": "ea1c88d1004f2d98d2b7ba4b32d0908403bec6267ea043193a71f7ae9eafd030",
      "release_date": "2025-06-30",
      "init_format": "sysconf",
      "devices": [
        "beagle-am67",
        "recommended"
      ]
    },
    {
      "name": "BeaglePlay Debian v6.12.x-ti XFCE (Recommended)",
      "description": "Debian Bookworm with the Xfce Desktop for BeaglePlay based on TI AM62 processor",
      "icon": "https://www.beagleboard.org/app/uploads/2022/10/debian.png",
      "url": "https://files.beagle.cc/file/beagleboard-public-2021/images/beagleplay-debian-12.11-xfce-v6.12-arm64-2025-06-30-12gb.img.xz",
      "extract_size": 12884901888,
      "extract_sha256": "78968e391f706735266406146040079925e12a51c6efff33be322b2c2f0dfe2e",
      "image_download_size": 1409854740,
      "image_download_sha256": "f9ffa8680ca76a23d7c7344ea780967b850852944ec8f9de2a2e070414748b48",
      "release_date": "2025-06-30",
      "init_format": "sysconf",
      "devices": [
        "beagle-am62",
        "recommended"
      ]
    },
    {
      "name": "BeaglePlay Debian v6.12.x-ti Minimal",
      "description": "Debian Bookworm with no desktop environment for BeaglePlay based on TI AM62 processor",
      "icon": "https://www.beagleboard.org/app/uploads/2022/10/debian.png",
      "url": "https://files.beagle.cc/file/beagleboard-public-2021/images/beagleplay-debian-12.11-minimal-v6.12-arm64-2025-06-30-8gb.img.xz",
      "extract_size": 7818182656,
      "extract_sha256": "87a06f88b25ea59dc32f46db4c96a796a7e8bf00ec65a04a48754803035dcb25",
      "image_download_size": 625325360,
      "image_download_sha256": "a866787ad6eb56774e3d1f42968f2025f60ad0cb133650071c5b265ac3c6adcb",
      "release_date": "2025-06-30",
      "init_format": "sysconf",
      "devices": [
        "beagle-am62",
        "recommended"
      ]
    },
    {
      "name": "PocketBeagle 2 Debian v6.12.x-ti IoT (Recommended)",
      "description": "Debian Bookworm with no desktop environment for PocketBeagle 2 based on TI AM62 processor",
      "icon": "https://www.beagleboard.org/app/uploads/2022/10/debian.png",
      "url": "https://files.beagle.cc/file/beagleboard-public-2021/images/pocketbeagle2-debian-12.11-iot-v6.12-arm64-2025-06-03-8gb.img.xz",
      "extract_size": 7818182656,
      "extract_sha256": "42ec6d100a60735bdedcb4aac6e721e5b507c1dbc150724d96f9e79893739d56",
      "image_download_size": 824268292,
      "image_download_sha256": "9ace54013cedaffcd56f71e601816f1b62b695cdb51bf2c2dcb3ad0a68f3279b",
      "release_date": "2025-06-03",
      "init_format": "sysconf",
      "devices": [
        "pocketbeagle2-am62",
        "recommended"
      ]
    },
    {
      "name": "PocketBeagle 2 Debian 13 v6.12.x-ti IoT (Workshop)",
      "description": "Debian 13 (Trixie) with no desktop environment for PocketBeagle 2 based on TI AM62 processor",
      "icon": "https://www.beagleboard.org/app/uploads/2022/10/debian.png",
      "url": "https://files.beagle.cc/file/beagleboard-public-2021/images/pocketbeagle2-debian-13-iot-v6.12-arm64-2025-06-11-8gb.img.xz",
      "extract_size": 7818182656,
      "extract_sha256": "ec350e6a4619418e8883ef641a489b34e69cc58b5b21c436bd5d9681d9427a0f",
      "image_download_size": 839417688,
      "image_download_sha256": "f9f8ff5bd4b09a45ba55f996fea5fe1501f7f4484c0d41fc27312360b3f8c153",
      "release_date": "2025-06-11",
      "init_format": "sysconf",
      "devices": [
        "pocketbeagle2-am62",
        "recommended"
      ]
    },
    {
      "name": "PocketBeagle 2 Debian v6.12.x-ti Minimal (Recommended)",
      "description": "Debian Bookworm with no desktop environment for PocketBeagle 2 based on TI AM62 processor",
      "icon": "https://www.beagleboard.org/app/uploads/2022/10/debian.png",
      "url": "https://files.beagle.cc/file/beagleboard-public-2021/images/pocketbeagle2-debian-12.11-minimal-v6.12-arm64-2025-06-03-8gb.img.xz",
      "extract_size": 7818182656,
      "extract_sha256": "6b4e8f195d7450b32a90af1af88283b17e53f668c01e685fe5da0a5c4666447f",
      "image_download_size": 631844712,
      "image_download_sha256": "512f40ded7aef549d2dac918bf3ac64d52da1005f343baab37a4ac63df8842af",
      "release_date": "2025-06-03",
      "init_format": "sysconf",
      "devices": [
        "pocketbeagle2-am62",
        "recommended"
      ]
    },
    {
      "name": "BeagleBone AI-64 Debian v6.12.x-ti XFCE (Recommended)",
      "description": "Debian Bookworm with the Xfce Desktop for BeagleBone AI-64 based on TI TDA4VM processor",
      "icon": "https://www.beagleboard.org/app/uploads/2022/10/debian.png",
      "url": "https://files.beagle.cc/file/beagleboard-public-2021/images/bbai64-debian-12.11-xfce-v6.12-arm64-2025-05-21-12gb.img.xz",
      "extract_size": 12884901888,
      "extract_sha256": "bbee53f9a1f50f9fd63ce6a94dfe600393be688232283623f1836b4da863fd99",
      "image_download_size": 1417335108,
      "image_download_sha256": "9d6ab31f05d1507395ea6817c852556dabbb91181211af8eea5d70e63be61117",
      "release_date": "2025-05-21",
      "init_format": "sysconf",
      "devices": [
        "beagle-tda4vm",
        "recommended"
      ]
    },
    {
      "name": "BeagleBone AI-64 Debian v6.12.x-ti Minimal",
      "description": "Debian Bookworm with no desktop environment for BeagleBone AI-64 based on TI TDA4VM processor",
      "icon": "https://www.beagleboard.org/app/uploads/2022/10/debian.png",
      "url": "https://files.beagle.cc/file/beagleboard-public-2021/images/bbai64-debian-12.11-minimal-v6.12-arm64-2025-06-30-8gb.img.xz",
      "extract_size": 7818182656,
      "extract_sha256": "09b205de68edec57c774fe6cafc45c8264e503928efdf39847fd4bc41e46423c",
      "image_download_size": 623933368,
      "image_download_sha256": "35208a40cff6aa1ec0b1bbe4a2259684ecd1d698d25a9a331853a88e5eba3562",
      "release_date": "2025-06-30",
      "init_format": "sysconf",
      "devices": [
        "beagle-tda4vm",
        "recommended"
      ]
    },
    {
      "name": "BeagleBone Black v6.12.x (LTS) VSCode",
      "description": "Debian Bookworm with no desktop environment for BeagleBone Black based on TI AM335x processor",
      "icon": "https://www.beagleboard.org/app/uploads/2022/10/debian.png",
      "url": "https://files.beagle.cc/file/beagleboard-public-2021/images/am335x-debian-12.11-base-vscode-v6.12-armhf-2025-06-30-4gb.img.xz",
      "extract_size": 3774873600,
      "extract_sha256": "f5af4ac787169bbb81bd3e79cec4b79f186a00ed04496242e362750b40d95aeb",
      "image_download_size": 414139160,
      "image_download_sha256": "e138d35ebb5e2e29007153f1e2bde5556df4e55c8f4c5f38855f8053b4188249",
      "release_date": "2025-06-30",
      "init_format": "sysconf",
      "devices": [
        "beagle-am335",
        "recommended"
      ]
    },
    {
      "name": "BeagleBone Black v6.15.x (Stable) VSCode",
      "description": "Debian Bookworm with no desktop environment for BeagleBone Black based on TI AM335x processor",
      "icon": "https://www.beagleboard.org/app/uploads/2022/10/debian.png",
      "url": "https://files.beagle.cc/file/beagleboard-public-2021/images/am335x-debian-12.11-base-vscode-v6.15-armhf-2025-06-30-4gb.img.xz",
      "extract_size": 3774873600,
      "extract_sha256": "de7cd193c986df3b4f6ea2fac8a532257e1525fd867df2e6fd9dd7d8caeb1542",
      "image_download_size": 414623892,
      "image_download_sha256": "54db5fc30a4432454ac688b610b2f3a2568f609cc49f63c4da1ca3ebfa6f44f1",
      "release_date": "2025-06-30",
      "init_format": "sysconf",
      "devices": [
        "beagle-am335",
        "recommended"
      ]
    },
    {
      "name": "eMMC Flashing (other)",
      "description": "These images will Flash the onboard eMMC on first bootup",
      "icon": "https://www.beagleboard.org/app/uploads/2022/10/debian.png",
      "subitems": [
        {
          "name": "BeaglePlay Debian v6.12.x-ti eMMC XFCE Flasher (Recommended)",
          "description": "Debian Bookworm with the Xfce Desktop for BeaglePlay based on TI AM62 processor",
          "icon": "https://www.beagleboard.org/app/uploads/2022/10/debian.png",
          "url": "https://files.beagle.cc/file/beagleboard-public-2021/images/beagleplay-emmc-flasher-debian-12.11-xfce-v6.12-arm64-2025-06-30-12gb.img.xz",
          "extract_size": 12884901888,
          "extract_sha256": "45748acdf87f926bfdc4b71fad3e0b357032542b4cf81bcbfd06df01f6cfd0d2",
          "image_download_size": 1411672756,
          "image_download_sha256": "f9a25af5206a519b823aa41a783473d26d4c645200cd2a28c17a8a33e4852dae",
          "release_date": "2025-06-30",
          "init_format": "sysconf",
          "devices": [
            "beagle-am62",
            "recommended"
          ]
        },
        {
          "name": "BeaglePlay Debian v6.12.x-ti eMMC Minimal Flasher",
          "description": "Debian Bookworm with no desktop environment for BeaglePlay based on TI AM62 processor",
          "icon": "https://www.beagleboard.org/app/uploads/2022/10/debian.png",
          "url": "https://files.beagle.cc/file/beagleboard-public-2021/images/beagleplay-emmc-flasher-debian-12.11-minimal-v6.12-arm64-2025-06-30-8gb.img.xz",
          "extract_size": 7818182656,
          "extract_sha256": "e720d249272096e8d9c676c68f860d8c3b753f5a1f99e9c45dfba8f13bfcfef6",
          "image_download_size": 622101796,
          "image_download_sha256": "a1a674b9458dffd905b906422eda91aeafbecd15f1043babd7b6cc3af4948aab",
          "release_date": "2025-06-30",
          "init_format": "sysconf",
          "devices": [
            "beagle-am62",
            "recommended"
          ]
        },
        {
          "name": "BeagleBone AI-64 Debian v6.12.x-ti eMMC XFCE Flasher (Recommended)",
          "description": "Debian Bookworm with the Xfce Desktop for BeagleBone AI-64 based on TI TDA4VM processor",
          "icon": "https://www.beagleboard.org/app/uploads/2022/10/debian.png",
          "url": "https://files.beagle.cc/file/beagleboard-public-2021/images/bbai64-emmc-flasher-debian-12.11-xfce-v6.12-arm64-2025-05-21-12gb.img.xz",
          "extract_size": 12884901888,
          "extract_sha256": "2112e6c5864e13c2bd21a08c4903db19c5fbf2611a446921b1f8fa88fc4da942",
          "image_download_size": 1418183768,
          "image_download_sha256": "98c98f695347fc2e9ca58ea796fbf75fc0f3d39cc8491ef34cd7356f0942a801",
          "release_date": "2025-05-21",
          "init_format": "sysconf",
          "devices": [
            "beagle-tda4vm",
            "recommended"
          ]
        },
        {
          "name": "BeagleBone AI-64 Debian v6.12.x-ti eMMC Minimal Flasher",
          "description": "Debian Bookworm with no desktop environment for BeagleBone AI-64 based on TI TDA4VM processor",
          "icon": "https://www.beagleboard.org/app/uploads/2022/10/debian.png",
          "url": "https://files.beagle.cc/file/beagleboard-public-2021/images/bbai64-emmc-flasher-debian-12.11-minimal-v6.12-arm64-2025-05-21-8gb.img.xz",
          "extract_size": 7818182656,
          "extract_sha256": "02c5603a0c5a47850372c822f19591ecaeb27b16a774ebc40ec94ffb8bfd0a62",
          "image_download_size": 636583424,
          "image_download_sha256": "fd17a8c89d844412c195bc907b3aca0adea605359dc3c5906a19d718784aca02",
          "release_date": "2025-05-21",
          "init_format": "sysconf",
          "devices": [
            "beagle-tda4vm",
            "recommended"
          ]
        }
      ]
    },
    {
      "name": "Testing Images (other)",
      "description": "Here be Dragons, images for testing!!!",
      "icon": "https://www.beagleboard.org/app/uploads/2022/10/debian.png",
      "subitems": [
        {
          "name": "BeagleY-AI Debian v6.12.x-ti Testing XFCE",
          "description": "Debian Bookworm with the Xfce Desktop for BeagleY-AI based on TI AM67A (J722S) processor",
          "icon": "https://www.beagleboard.org/app/uploads/2022/10/debian.png",
          "url": "https://files.beagle.cc/file/beagleboard-public-2021/images/beagley-ai-debian-12.11-xfce-v6.12-arm64-2025-06-30-12gb.img.xz",
          "extract_size": 12884901888,
          "extract_sha256": "829e83e0369757f11e9e98e1161afbe8188d98771fe6565fe58d5016713efdda",
          "image_download_size": 1409902028,
          "image_download_sha256": "975a920dcf5127e3d8731bedf5b5cf9a931ef90b50509fd38d5c2d3a9857f311",
          "release_date": "2025-06-30",
          "init_format": "sysconf",
          "devices": [
            "beagle-am67",
            "recommended"
          ]
        },
        {
          "name": "BeagleY-AI Debian v6.6.x-ti Testing XFCE",
          "description": "Debian Bookworm with the Xfce Desktop for BeagleY-AI based on TI AM67A (J722S) processor",
          "icon": "https://www.beagleboard.org/app/uploads/2022/10/debian.png",
          "url": "https://files.beagle.cc/file/beagleboard-public-2021/images/beagley-ai-debian-12.11-xfce-v6.6-arm64-2025-06-30-12gb.img.xz",
          "extract_size": 12884901888,
          "extract_sha256": "0889530975ed0c5859e15c5df765ba017c2592361bd8f5eaa7c83e41b59f7874",
          "image_download_size": 1406281984,
          "image_download_sha256": "dd476254b8589ac3987deb10b58a8967034878a4b3f294e8e33db3834fb2744a",
          "release_date": "2025-06-30",
          "init_format": "sysconf",
          "devices": [
            "beagle-am67",
            "recommended"
          ]
        }
      ]
    }
  ]
}
